irolog/__init__.py
irolog/formatter.py
irolog-0.0.1.dist-info/LICENSE
irolog-0.0.1.dist-info/METADATA
irolog-0.0.1.dist-info/WHEEL
irolog-0.0.1.dist-info/top_level.txt
irolog-0.0.1.dist-info/RECORD
