Metadata-Version: 2.1
Name: irolog
Version: 0.0.1
Summary: A formatter for use with the python logger module to print colorful output to console
Home-page: https://github.com/SandeepGusain/irolog
Author: Sandeep Gusain
Author-email: sandeep.gusain3761@gmail.com
License: UNKNOWN
Project-URL: Bug Tracker, https://github.com/irolog/SandeepGusain/issues
Platform: UNKNOWN
Classifier: Programming Language :: Python :: 3
Classifier: License :: OSI Approved :: MIT License
Classifier: Operating System :: OS Independent
Requires-Python: >=3.4
